langchain_icosa/__init__.py
langchain_icosa/combinatorial_reasoning.py
langchain_icosa-1.1.2.dist-info/LICENSE
langchain_icosa-1.1.2.dist-info/METADATA
langchain_icosa-1.1.2.dist-info/WHEEL
langchain_icosa-1.1.2.dist-info/top_level.txt
langchain_icosa-1.1.2.dist-info/RECORD
