Metadata-Version: 2.1
Name: langchain_icosa
Version: 1.1.2
Summary: LangChain plugin for Icosa Computing's Combinatorial Reasoning generative AI pipeline.
Author-email: Icosa Computing <vmittal@icosacomputing.com>
License: MIT License
Project-URL: Homepage, https://github.com/Icosa-Computing/langchain-icosa
Project-URL: Repository, https://github.com/Icosa-Computing/langchain-icosa
Classifier: Programming Language :: Python :: 3
Classifier: License :: OSI Approved :: MIT License
Classifier: Operating System :: OS Independent
Requires-Python: >=3.8
License-File: LICENSE
Requires-Dist: langchain-core ==0.2.24
Requires-Dist: requests ==2.32.3
Requires-Dist: openai ==1.37.1
Requires-Dist: langchain-openai ==0.1.19
